devcloud/Devcloud.py
devcloud/__init__.py
devcloud/common.py
devcloud/container.py
devcloud/edgenode.py
devcloud/environment.json
devcloud/project.py
devcloud/result.py
devcloud-2023.4.2.data/data/devcloud/environment.json
devcloud-2023.4.2.dist-info/LICENSE
devcloud-2023.4.2.dist-info/METADATA
devcloud-2023.4.2.dist-info/WHEEL
devcloud-2023.4.2.dist-info/top_level.txt
devcloud-2023.4.2.dist-info/RECORD
