Metadata-Version: 2.1
Name: devcloud
Version: 2023.4.2
Summary: Intel® Devcloud - Developer Cloud for the Edge Python library
Home-page: https://github.com/intel/DevCloudContent-git
License: OSI Approved :: Apache License, Version 2.0
Classifier: Programming Language :: Python :: 3
Classifier: Operating System :: OS Independent
Requires-Python: >=3.6
License-File: LICENSE
Requires-Dist: requests (==2.28.2)
Requires-Dist: pyjwt (==2.6.0)
Requires-Dist: typer
Requires-Dist: pandas
Requires-Dist: tabulate
Requires-Dist: Pillow (==9.4.0)
Requires-Dist: importlib-resources (==5.4.0)
